matheus_finance_dio/__init__.py
matheus_finance_dio/module1.py
matheus_finance_dio-0.0.1.dist-info/METADATA
matheus_finance_dio-0.0.1.dist-info/WHEEL
matheus_finance_dio-0.0.1.dist-info/top_level.txt
matheus_finance_dio-0.0.1.dist-info/RECORD
