Metadata-Version: 2.1
Name: matheus-finance-dio
Version: 0.0.1
Summary: Pacote básico para cálculo de valor presente de títulos públicos
Home-page: https://github.com/matheus-brito-dev/simple-package-template
Author: Matheus Brito
Author-email: mabrol23@gmail.com
License: MIT
Platform: UNKNOWN
Requires-Python: >=3.8
